Metadata-Version: 1.0
Name: nocps
Version: 0.1
Summary: API for NOC-PS provisioning system
Home-page: https://github.com/noonedeadpunk/nocps/
Author: Dmytro Rabotiahov
Author-email: contact@nodead.net
License: MIT
Platform: UNKNOWN
